[
    {
        "id": "part-1",
        "challengeId": "challenge-1",
        "userId": "user-1",
        "currentProgress": 143250,
        "lastUpdated": "2026-01-18T20:00:00Z",
        "streakDays": 18
    },
    {
        "id": "part-2",
        "challengeId": "challenge-1",
        "userId": "user-2",
        "currentProgress": 156780,
        "lastUpdated": "2026-01-18T21:00:00Z",
        "streakDays": 17
    },
    {
        "id": "part-3",
        "challengeId": "challenge-1",
        "userId": "user-3",
        "currentProgress": 128900,
        "lastUpdated": "2026-01-18T19:00:00Z",
        "streakDays": 14
    },
    {
        "id": "part-4",
        "challengeId": "challenge-2",
        "userId": "user-1",
        "currentProgress": 3,
        "lastUpdated": "2026-01-17T22:00:00Z",
        "streakDays": 3
    },
    {
        "id": "part-5",
        "challengeId": "challenge-2",
        "userId": "user-2",
        "currentProgress": 2,
        "lastUpdated": "2026-01-15T20:00:00Z",
        "streakDays": 2
    },
    {
        "id": "part-6",
        "challengeId": "challenge-4",
        "userId": "user-1",
        "currentProgress": 18,
        "lastUpdated": "2026-01-18T07:00:00Z",
        "streakDays": 18
    },
    {
        "id": "part-7",
        "challengeId": "challenge-4",
        "userId": "user-2",
        "currentProgress": 15,
        "lastUpdated": "2026-01-18T06:30:00Z",
        "streakDays": 15
    }
]